{"createdAt":"2021-05-18T15:16:36.828","modifiedAt":"2021-11-03T11:23:53.914","createdBy":"TAS","modifiedBy":"TAS","title":"SE - Balance Monitor - Aggregated Balance","provider":"SpringBackendServiceProvider","tags":[],"systemTags":["services-editor","published-as-datasource","RESERVED_DOCUMENT"],"name":"SE - Balance Monitor - Aggregated Balance","type":"services-editor","saved":true,"id":"f57bed74-7974-4199-b64b-19143166d70e","previewId":null,"content":{"definition":{"id":"f57bed74-7974-4199-b64b-19143166d70e","title":"SE - Balance Monitor - Aggregated Balance","useBaseUrl":true,"publishAsDatasource":true,"serverSideDatasource":true,"dataEntryEnabled":false,"downloadEnabled":false,"expectedResultType":"Table","validated":true,"mandatoryParameters":[],"skipOnEmptyQueryString":false,"includeRawData":false,"emptyParametersToEmptyString":false,"schema":[{"name":"country","type":"string","value":"LU"},{"name":"codRefCurrency","type":"string","value":"EUR"},{"name":"balanceName","type":"string","value":"DEPOSITORY-LU-GBP"},{"name":"kind","type":"string","value":"aggregatedbalanceresource#list"},{"name":"correspondentType","type":"string","value":"NOSTRO"},{"name":"balancename","type":"string","value":null},{"name":"currentBalance","type":"number","value":8465554321.75991},{"name":"nostroType","type":"string","value":"DEPOSITORY"},{"name":"currency","type":"string","value":"GBP"},{"name":"countervalueRefCurrency","type":"number","value":10616710933.8}],"selectCall":{"method":"Get","enabled":true,"serverSide":false,"serverSideUrlParametersEncoded":false,"serverSideUseCallerHeaders":false,"virtual":false,"responseType":"json","transformerOut":{"schema":{},"expectedResult":null,"syntax":"standard","code":"{}"},"transformerIn":{"schema":{"datasource":{},"parameter":{},"systemParameter":{},"custom":{"result":{"fields":[null]}}},"expectedResult":null,"syntax":"standard","code":"custom('result').items;"},"headers":[],"address":{"schema":{"datasource":{},"parameter":{"take":{"id":"b56547b1-7ce7-2569-aacf-ca48b3ce1347"},"serviceType":{"id":"b7048725-ce9b-9204-24cc-e44af94c39e9"},"nostroAccountType":{"id":"d60e0981-aba3-7916-ce9a-5c1280f457c2"},"legalEntity":{"id":"e7799ed3-75b6-c8c8-8682-a9493c74154e"},"currency":{"id":"8b4324f9-bab9-ccea-125b-56c354e67ec7"},"systemAccountCode":{"id":"1964eec5-c61d-1297-f629-41e644652685"},"legalEntityAccount":{"id":"fdea1fb4-a096-8e31-7756-2c64fb18d7b4"},"accountOwner":{"id":"69cc3353-c8c2-2d28-bc1a-53533e67e6a6"},"country":{"id":"6751aa0c-847e-5c36-8c25-31942558653d"},"client":{"id":"9bc21de5-c6df-36bd-2a62-f632952a3dfe"},"businessDate":{"id":"d4208649-55d3-abcb-cc3c-d9dae38f3162"},"correspondentType":{"id":"be7adce8-6554-35e3-b214-eec73501fe9a"}},"systemParameter":{},"custom":{"page":{"fields":[null]},"pageSize":{"fields":[null]},"remoteSort":{"fields":[null]}}},"expectedResult":null,"syntax":"web-template","code":"corrbanks/rs/aggregatedbalance?take=<%= parameter('take') %>&page=<%= custom('page') %>&pageSize=<%= custom('pageSize') %>&skip=0&serviceType=<%= parameter('serviceType') %>&nostroAccountType=<%= parameter('nostroAccountType') %>&legalEntity=<%= parameter('legalEntity') %>&currency=<%= parameter('currency') %>&systemAccountCode=<%= parameter('systemAccountCode') %>&legalEntityAccount=<%= parameter('legalEntityAccount') %>&accountOwner=<%= parameter('accountOwner') %>&country=<%= parameter('country') %>&client=<%= parameter('client') %>&businessDate=<%= format(parameter('businessDate'),'yyyy-MM-dd') %><%=(parameter('correspondentType') && parameter('correspondentType').trim().length>0)?'&correspondentType='+encodeURIComponent(parameter('correspondentType')):''%>&<%= (encodeAquariusSortParams(custom('remoteSort'))=='sort[0][field]=&sort[0][dir]=asc')?'sort[0][field]=countervalueRefCurrency&sort[0][dir]=asc':encodeAquariusSortParams(custom('remoteSort'))%>"},"type":"Select","errorBypass":{"schema":{},"expectedResult":null,"syntax":"standard"}},"insertCall":{"method":"Put","enabled":false,"serverSide":false,"serverSideUrlParametersEncoded":false,"serverSideUseCallerHeaders":false,"virtual":false,"responseType":"json","transformerOut":{"schema":{},"expectedResult":null,"syntax":"standard","code":"{}"},"transformerIn":{"schema":{},"expectedResult":null,"syntax":"standard","code":"custom('result');"},"headers":[],"address":{"schema":{},"expectedResult":null,"syntax":"web-template"},"type":"Insert","errorBypass":{"schema":{},"expectedResult":null,"syntax":"standard"}},"updateCall":{"method":"Post","enabled":false,"serverSide":false,"serverSideUrlParametersEncoded":false,"serverSideUseCallerHeaders":false,"virtual":false,"responseType":"json","transformerOut":{"schema":{},"expectedResult":null,"syntax":"standard","code":"{}"},"transformerIn":{"schema":{},"expectedResult":null,"syntax":"standard","code":"custom('result');"},"headers":[],"address":{"schema":{},"expectedResult":null,"syntax":"web-template"},"type":"Update","errorBypass":{"schema":{},"expectedResult":null,"syntax":"standard"}},"deleteCall":{"method":"Delete","enabled":false,"serverSide":false,"serverSideUrlParametersEncoded":false,"serverSideUseCallerHeaders":false,"virtual":false,"responseType":"json","transformerOut":{"schema":{},"expectedResult":null,"syntax":"standard","code":"{}"},"transformerIn":{"schema":{},"expectedResult":null,"syntax":"standard","code":"custom('result');"},"headers":[],"address":{"schema":{},"expectedResult":null,"syntax":"web-template"},"type":"Delete","errorBypass":{"schema":{},"expectedResult":null,"syntax":"standard"}},"createCall":{"method":"Get","enabled":false,"serverSide":false,"serverSideUrlParametersEncoded":false,"serverSideUseCallerHeaders":false,"virtual":false,"responseType":"json","transformerOut":{"schema":{},"expectedResult":null,"syntax":"standard","code":"{}"},"transformerIn":{"schema":{},"expectedResult":null,"syntax":"standard","code":"custom('result');"},"headers":[],"address":{"schema":{},"expectedResult":null,"syntax":"web-template"},"type":"Create","errorBypass":{"schema":{},"expectedResult":null,"syntax":"standard"}},"serverSideOptions":{"id":"de4b1cac-27e3-a42d-134e-f85d57aeb510","columns":[],"rows":[],"originalRows":[],"dataEntryRunTypes":[],"datasourceType":"Standard","autoRefreshEnabled":false,"autoRefreshSystem":false,"autoRefreshTime":60,"refreshOnLoad":false,"remoteSort":"","page":1,"isBusy":false,"isFiltered":false,"isServerSide":false,"hasError":false,"splitItems":[],"rowCount":100,"pageSize":10,"tags":[],"parameters":[]},"pageExp":{"schema":{"datasource":{},"parameter":{},"systemParameter":{},"custom":{"result":{"fields":[null]}}},"expectedResult":null,"syntax":"standard","code":"(custom('result')||{}).page||1;"},"pageSizeExp":{"schema":{"datasource":{},"parameter":{},"systemParameter":{},"custom":{"pageSize":{"fields":[null]}}},"expectedResult":null,"syntax":"standard","code":"custom('pageSize')"},"recordCountExp":{"schema":{"datasource":{},"parameter":{},"systemParameter":{},"custom":{"result":{"fields":[null]}}},"expectedResult":null,"syntax":"standard","code":"(custom('result')||{}).total||0;"},"sortingExp":{"schema":{},"expectedResult":null,"syntax":"standard"},"downloadExp":{"schema":{},"expectedResult":null,"syntax":"web-template"},"baseUrlId":"Aquarius Services","resultTypes":"Table"},"parameters":[{"id":"b56547b1-7ce7-2569-aacf-ca48b3ce1347","name":"take","description":"","systemType":"","defaultValue":null,"lookupItems":[],"isHidden":false,"isMultiSelect":false,"isReadOnly":false,"isOptional":false,"popupWidth":300,"isSearchAllowed":false,"ravenParameterType":"normal","ravenDatatype":"string","lookup":{"mode":"standard","showSearchBox":true,"allowSort":true,"bindings":[],"columns":[]},"rules":[],"tags":[],"value":"5","expression":{"schema":{},"expectedResult":null,"syntax":"standard"}},{"id":"dcca89f6-caba-b91b-1e8d-42666603bf44","name":"page","description":"","systemType":"","defaultValue":null,"lookupItems":[],"isHidden":false,"isMultiSelect":false,"isReadOnly":false,"isOptional":false,"popupWidth":300,"isSearchAllowed":false,"ravenParameterType":"normal","ravenDatatype":"string","lookup":{"mode":"standard","showSearchBox":true,"allowSort":true,"bindings":[],"columns":[]},"rules":[],"tags":[],"value":"1","expression":{"schema":{},"expectedResult":null,"syntax":"standard"}},{"id":"8d77d3b2-57a6-7580-d9de-1f8b62f69874","name":"pageSize","description":"","systemType":"","defaultValue":null,"lookupItems":[],"isHidden":false,"isMultiSelect":false,"isReadOnly":false,"isOptional":false,"popupWidth":300,"isSearchAllowed":false,"ravenParameterType":"normal","ravenDatatype":"string","lookup":{"mode":"standard","showSearchBox":true,"allowSort":true,"bindings":[],"columns":[]},"rules":[],"tags":[],"value":"10","expression":{"schema":{},"expectedResult":null,"syntax":"standard"}},{"id":"a76e9518-dab4-4868-3cfa-3e9ac68e15d5","name":"skip","description":"","systemType":"","defaultValue":null,"lookupItems":[],"isHidden":false,"isMultiSelect":false,"isReadOnly":false,"isOptional":false,"popupWidth":300,"isSearchAllowed":false,"ravenParameterType":"normal","ravenDatatype":"string","lookup":{"mode":"standard","showSearchBox":true,"allowSort":true,"bindings":[],"columns":[]},"rules":[],"tags":[],"value":"0","expression":{"schema":{},"expectedResult":null,"syntax":"standard"}},{"id":"314bcff8-76c4-89fc-e372-c51524d6a8a2","name":"sort[0][field]","description":"","systemType":"","defaultValue":null,"lookupItems":[],"isHidden":false,"isMultiSelect":false,"isReadOnly":false,"isOptional":false,"popupWidth":300,"isSearchAllowed":false,"ravenParameterType":"normal","ravenDatatype":"string","lookup":{"mode":"standard","showSearchBox":true,"allowSort":true,"bindings":[],"columns":[]},"rules":[],"tags":[],"value":"countervalueRefCurrency","expression":{"schema":{},"expectedResult":null,"syntax":"standard"}},{"id":"97e7d4ee-5ad1-9c5e-0dea-c6e28e877aad","name":"sort[0][dir]","description":"","systemType":"","defaultValue":null,"lookupItems":[],"isHidden":false,"isMultiSelect":false,"isReadOnly":false,"isOptional":false,"popupWidth":300,"isSearchAllowed":false,"ravenParameterType":"normal","ravenDatatype":"string","lookup":{"mode":"standard","showSearchBox":true,"allowSort":true,"bindings":[],"columns":[]},"rules":[],"tags":[],"value":"desc","expression":{"schema":{},"expectedResult":null,"syntax":"standard"}},{"id":"b7048725-ce9b-9204-24cc-e44af94c39e9","name":"serviceType","description":"","systemType":"","defaultValue":null,"lookupItems":[],"isHidden":false,"isMultiSelect":false,"isReadOnly":false,"isOptional":false,"popupWidth":300,"isSearchAllowed":false,"ravenParameterType":"normal","ravenDatatype":"string","lookup":{"mode":"standard","showSearchBox":true,"allowSort":true,"bindings":[],"columns":[]},"rules":[],"tags":[],"value":"CORR","expression":{"schema":{},"expectedResult":null,"syntax":"standard"}},{"id":"d60e0981-aba3-7916-ce9a-5c1280f457c2","name":"nostroAccountType","description":"","systemType":"","defaultValue":null,"lookupItems":[],"isHidden":false,"isMultiSelect":false,"isReadOnly":false,"isOptional":false,"popupWidth":300,"isSearchAllowed":false,"ravenParameterType":"normal","ravenDatatype":"string","lookup":{"mode":"standard","showSearchBox":true,"allowSort":true,"bindings":[],"columns":[]},"rules":[],"tags":[],"expression":{"schema":{},"expectedResult":null,"syntax":"standard"}},{"id":"e7799ed3-75b6-c8c8-8682-a9493c74154e","name":"legalEntity","description":"","systemType":"","defaultValue":null,"lookupItems":[],"isHidden":false,"isMultiSelect":false,"isReadOnly":false,"isOptional":false,"popupWidth":300,"isSearchAllowed":false,"ravenParameterType":"normal","ravenDatatype":"string","lookup":{"mode":"standard","showSearchBox":true,"allowSort":true,"bindings":[],"columns":[]},"rules":[],"tags":[],"expression":{"schema":{},"expectedResult":null,"syntax":"standard"}},{"id":"8b4324f9-bab9-ccea-125b-56c354e67ec7","name":"currency","description":"","systemType":"","defaultValue":null,"lookupItems":[],"isHidden":false,"isMultiSelect":false,"isReadOnly":false,"isOptional":false,"popupWidth":300,"isSearchAllowed":false,"ravenParameterType":"normal","ravenDatatype":"string","lookup":{"mode":"standard","showSearchBox":true,"allowSort":true,"bindings":[],"columns":[]},"rules":[],"tags":[],"value":"","expression":{"schema":{},"expectedResult":null,"syntax":"standard"}},{"id":"1964eec5-c61d-1297-f629-41e644652685","name":"systemAccountCode","description":"","systemType":"","defaultValue":null,"lookupItems":[],"isHidden":false,"isMultiSelect":false,"isReadOnly":false,"isOptional":false,"popupWidth":300,"isSearchAllowed":false,"ravenParameterType":"normal","ravenDatatype":"string","lookup":{"mode":"standard","showSearchBox":true,"allowSort":true,"bindings":[],"columns":[]},"rules":[],"tags":[],"expression":{"schema":{},"expectedResult":null,"syntax":"standard"}},{"id":"fdea1fb4-a096-8e31-7756-2c64fb18d7b4","name":"legalEntityAccount","description":"","systemType":"","defaultValue":null,"lookupItems":[],"isHidden":false,"isMultiSelect":false,"isReadOnly":false,"isOptional":false,"popupWidth":300,"isSearchAllowed":false,"ravenParameterType":"normal","ravenDatatype":"string","lookup":{"mode":"standard","showSearchBox":true,"allowSort":true,"bindings":[],"columns":[]},"rules":[],"tags":[],"expression":{"schema":{},"expectedResult":null,"syntax":"standard"}},{"id":"69cc3353-c8c2-2d28-bc1a-53533e67e6a6","name":"accountOwner","description":"","systemType":"","defaultValue":null,"lookupItems":[],"isHidden":false,"isMultiSelect":false,"isReadOnly":false,"isOptional":false,"popupWidth":300,"isSearchAllowed":false,"ravenParameterType":"normal","ravenDatatype":"string","lookup":{"mode":"standard","showSearchBox":true,"allowSort":true,"bindings":[],"columns":[]},"rules":[],"tags":[],"expression":{"schema":{},"expectedResult":null,"syntax":"standard"}},{"id":"6751aa0c-847e-5c36-8c25-31942558653d","name":"country","description":"","systemType":"","defaultValue":null,"lookupItems":[],"isHidden":false,"isMultiSelect":false,"isReadOnly":false,"isOptional":false,"popupWidth":300,"isSearchAllowed":false,"ravenParameterType":"normal","ravenDatatype":"string","lookup":{"mode":"standard","showSearchBox":true,"allowSort":true,"bindings":[],"columns":[]},"rules":[],"tags":[],"expression":{"schema":{},"expectedResult":null,"syntax":"standard"}},{"id":"9bc21de5-c6df-36bd-2a62-f632952a3dfe","name":"client","description":"","systemType":"","defaultValue":null,"lookupItems":[],"isHidden":false,"isMultiSelect":false,"isReadOnly":false,"isOptional":false,"popupWidth":300,"isSearchAllowed":false,"ravenParameterType":"normal","ravenDatatype":"string","lookup":{"mode":"standard","showSearchBox":true,"allowSort":true,"bindings":[],"columns":[]},"rules":[],"tags":[],"expression":{"schema":{},"expectedResult":null,"syntax":"standard"}},{"id":"d4208649-55d3-abcb-cc3c-d9dae38f3162","name":"businessDate","description":"","systemType":"","defaultValue":"1970-01-01T00:00:00.000Z","lookupItems":[],"isHidden":false,"isMultiSelect":false,"isReadOnly":false,"isOptional":false,"popupWidth":300,"isSearchAllowed":false,"ravenParameterType":"normal","ravenDatatype":"date","lookup":{"mode":"standard","showSearchBox":true,"allowSort":true,"bindings":[],"columns":[]},"rules":[],"tags":[],"value":"2017-06-14T22:00:00.000Z","expression":{"schema":{},"expectedResult":null,"syntax":"standard"}},{"id":"be7adce8-6554-35e3-b214-eec73501fe9a","name":"correspondentType","description":"","systemType":"","defaultValue":null,"lookupItems":[],"isHidden":false,"isMultiSelect":false,"isReadOnly":false,"isOptional":false,"popupWidth":300,"isSearchAllowed":false,"ravenParameterType":"normal","ravenDatatype":"string","lookup":{"mode":"standard","showSearchBox":true,"allowSort":true,"bindings":[],"columns":[]},"rules":[],"tags":[],"value":"","expression":{"schema":{},"expectedResult":null,"syntax":"standard"}}]}}