{"createdAt":"2021-05-21T11:22:52.276","modifiedAt":"2021-06-15T18:03:41.270","createdBy":"TAS","modifiedBy":"TAS","title":"SE - Balance Monitor - Account Balance Detail","provider":"ServicesEditorBackendServiceProvider","tags":["Raven service"],"systemTags":["services-editor","published-as-datasource","RESERVED_DOCUMENT"],"name":"SE - Balance Monitor - Account Balance Detail","type":"services-editor","saved":false,"id":"1b263f22-b452-42bb-ae34-60cf085756e2","previewId":null,"content":{"definition":{"id":"1b263f22-b452-42bb-ae34-60cf085756e2","title":"SE - Balance Monitor - Account Balance Detail","useBaseUrl":true,"publishAsDatasource":true,"serverSideDatasource":false,"dataEntryEnabled":false,"downloadEnabled":false,"expectedResultType":"Table","validated":false,"mandatoryParameters":[],"skipOnEmptyQueryString":false,"includeRawData":false,"schema":[{"name":"serviceType","type":"string","value":"CORR"},{"name":"idAccount","type":"number","value":1565},{"name":"masterAccount","type":"string","value":null},{"name":"startOfDayBalanceTimestamp","type":"string","value":null},{"name":"toBeSettledPreadvicePayment","type":"number","value":0},{"name":"toBeSettledPayments","type":"number","value":0},{"name":"totalUnmatchedPayments","type":"number","value":0},{"name":"error","type":"string","value":null},{"name":"endOfDayBalance","type":"number","value":0},{"name":"legalEntity","type":"string","value":"CEDELULL"},{"name":"valueBalance","type":"number","value":610880162.95195},{"name":"toBeSettledSI","type":"number","value":0},{"name":"correspondentType","type":"string","value":"NOSTRO"},{"name":"client","type":"string","value":"BRLADE22"},{"name":"currency","type":"string","value":"JPY"},{"name":"id","type":"number","value":777775},{"name":"toBeSettledCA","type":"number","value":0},{"name":"bookBalance","type":"number","value":610880162.95195},{"name":"floor","type":"string","value":null},{"name":"ceiling","type":"string","value":null},{"name":"toBeSettledForecastSI","type":"number","value":0},{"name":"systemAccountCode","type":"string","value":"68585-JPY"},{"name":"startOfDayBalance","type":"number","value":0},{"name":"kind","type":"string","value":"accountbalancesresource#list"},{"name":"toBeSettledPreadviceCA","type":"number","value":0},{"name":"accountOwner","type":"string","value":"08094/WWWBDEFF"},{"name":"toBeSettledPreadviceSI","type":"number","value":0},{"name":"projectedBalance","type":"number","value":610880162.95195},{"name":"legalEntityAccountCode","type":"string","value":"7114512018"},{"name":"toBeSettledForecastPayment","type":"number","value":0},{"name":"nostroType","type":"string","value":"DEPOSITORY"},{"name":"toBeSettledBalance","type":"number","value":0},{"name":"countervalueBalance","type":"number","value":4811292.16},{"name":"toBeSettledForecastCA","type":"number","value":0},{"name":"valueBalanceTimestamp","type":"string","value":"2017-05-05 00:00:00"},{"name":"endOfDayBalanceTimestamp","type":"string","value":null}],"selectCall":{"method":"Get","enabled":true,"serverSide":false,"responseType":"json","transformerOut":{"schema":{},"expectedResult":null,"syntax":"standard","code":"{}"},"transformerIn":{"schema":{},"expectedResult":null,"syntax":"standard","code":"custom('result');"},"headers":[],"address":{"schema":{"datasource":{},"parameter":{"idBalance":{"id":"40666843-cb8c-2ce3-9694-ac73e43c15f0"}},"systemParameter":{},"custom":{}},"expectedResult":null,"syntax":"web-template","code":"corrbanks/rs/accountbalances/<%= parameter('idBalance') %>"},"type":"Select"},"insertCall":{"method":"Put","enabled":false,"serverSide":false,"responseType":"json","transformerOut":{"schema":{},"expectedResult":null,"syntax":"standard","code":"{}"},"transformerIn":{"schema":{},"expectedResult":null,"syntax":"standard","code":"custom('result');"},"headers":[],"address":{"schema":{},"expectedResult":null,"syntax":"web-template"},"type":"Insert"},"updateCall":{"method":"Post","enabled":false,"serverSide":false,"responseType":"json","transformerOut":{"schema":{},"expectedResult":null,"syntax":"standard","code":"{}"},"transformerIn":{"schema":{},"expectedResult":null,"syntax":"standard","code":"custom('result');"},"headers":[],"address":{"schema":{},"expectedResult":null,"syntax":"web-template"},"type":"Update"},"deleteCall":{"method":"Delete","enabled":false,"serverSide":false,"responseType":"json","transformerOut":{"schema":{},"expectedResult":null,"syntax":"standard","code":"{}"},"transformerIn":{"schema":{},"expectedResult":null,"syntax":"standard","code":"custom('result');"},"headers":[],"address":{"schema":{},"expectedResult":null,"syntax":"web-template"},"type":"Delete"},"createCall":{"method":"Get","enabled":false,"serverSide":false,"responseType":"json","transformerOut":{"schema":{},"expectedResult":null,"syntax":"standard","code":"{}"},"transformerIn":{"schema":{},"expectedResult":null,"syntax":"standard","code":"custom('result');"},"headers":[],"address":{"schema":{},"expectedResult":null,"syntax":"web-template"},"type":"Create"},"serverSideOptions":{"id":"4534c822-0e20-4e22-727c-bc29cc085f51","columns":[],"rows":[],"originalRows":[],"dataEntryRunTypes":[],"datasourceType":"Standard","autoRefreshEnabled":false,"autoRefreshSystem":false,"autoRefreshTime":60,"remoteSort":"","page":1,"isBusy":false,"isFiltered":false,"isServerSide":false,"hasError":false,"splitItems":[],"rowCount":100,"pageSize":10,"tags":[],"parameters":[]},"pageExp":{"schema":{},"expectedResult":null,"syntax":"standard"},"pageSizeExp":{"schema":{},"expectedResult":null,"syntax":"standard"},"recordCountExp":{"schema":{},"expectedResult":null,"syntax":"standard"},"sortingExp":{"schema":{},"expectedResult":null,"syntax":"standard"},"downloadExp":{"schema":{},"expectedResult":null,"syntax":"web-template"},"baseUrlId":"Aquarius Services"},"parameters":[{"id":"40666843-cb8c-2ce3-9694-ac73e43c15f0","name":"idBalance","description":"","systemType":"","defaultValue":null,"lookupItems":[],"isHidden":false,"isMultiSelect":false,"isReadOnly":false,"isOptional":false,"popupWidth":300,"isSearchAllowed":false,"ravenParameterType":"normal","ravenDatatype":"string","lookup":{"mode":"standard","showSearchBox":true,"allowSort":true,"bindings":[],"columns":[]},"rules":[],"tags":[],"value":"777775"}]}}