{"createdAt":"2021-06-03T16:04:39.765","modifiedAt":"2021-06-07T10:45:37.643","createdBy":"TAS","modifiedBy":"TAS","title":"Forecast journal Select Cut Off Time","provider":"ServicesEditorBackendServiceProvider","tags":["Raven service"],"systemTags":["published-as-datasource","services-editor","RESERVED_DOCUMENT"],"name":"Forecast journal Select Cut Off Time","type":"services-editor","saved":false,"id":"5e5c41bc-282b-42cf-b689-7bccfc917c16","previewId":null,"content":{"definition":{"id":"5e5c41bc-282b-42cf-b689-7bccfc917c16","title":"Forecast journal Select Cut Off Time","useBaseUrl":true,"publishAsDatasource":true,"serverSideDatasource":false,"dataEntryEnabled":false,"downloadEnabled":false,"expectedResultType":"Table","validated":false,"mandatoryParameters":[],"skipOnEmptyQueryString":false,"includeRawData":false,"schema":[{"name":"kind","type":"string","value":"cutofftimevresource#list"},{"name":"description","type":"string","value":"01:00-Primo CLS Pay-In Schedule"},{"name":"traslatedCutoffTime","type":"number","value":10000},{"name":"id","type":"number","value":29},{"name":"codIntParticipant","type":"string","value":null},{"name":"event","type":"string","value":"Primo CLS Pay-In Schedule"}],"selectCall":{"method":"Get","enabled":true,"serverSide":false,"responseType":"json","transformerOut":{"schema":{},"expectedResult":null,"syntax":"standard","code":"{}"},"transformerIn":{"schema":{"datasource":{},"parameter":{},"systemParameter":{},"custom":{"result":{"fields":[null]}}},"expectedResult":null,"syntax":"standard","code":"custom('result').items;"},"headers":[],"address":{"schema":{"datasource":{},"parameter":{"idCategory":{"id":"24c0d9f9-5a33-6e1f-8784-8e432dbec314"}},"systemParameter":{},"custom":{}},"expectedResult":null,"syntax":"web-template","code":"foundation/rs/forecast/cutofftimes?idCategory=<%= parameter('idCategory') %>"},"type":"Select"},"insertCall":{"method":"Put","enabled":false,"serverSide":false,"responseType":"json","transformerOut":{"schema":{},"expectedResult":null,"syntax":"standard","code":"{}"},"transformerIn":{"schema":{},"expectedResult":null,"syntax":"standard","code":"custom('result');"},"headers":[],"address":{"schema":{},"expectedResult":null,"syntax":"web-template"},"type":"Insert"},"updateCall":{"method":"Post","enabled":false,"serverSide":false,"responseType":"json","transformerOut":{"schema":{},"expectedResult":null,"syntax":"standard","code":"{}"},"transformerIn":{"schema":{},"expectedResult":null,"syntax":"standard","code":"custom('result');"},"headers":[],"address":{"schema":{},"expectedResult":null,"syntax":"web-template"},"type":"Update"},"deleteCall":{"method":"Delete","enabled":false,"serverSide":false,"responseType":"json","transformerOut":{"schema":{},"expectedResult":null,"syntax":"standard","code":"{}"},"transformerIn":{"schema":{},"expectedResult":null,"syntax":"standard","code":"custom('result');"},"headers":[],"address":{"schema":{},"expectedResult":null,"syntax":"web-template"},"type":"Delete"},"createCall":{"method":"Get","enabled":false,"serverSide":false,"responseType":"json","transformerOut":{"schema":{},"expectedResult":null,"syntax":"standard","code":"{}"},"transformerIn":{"schema":{},"expectedResult":null,"syntax":"standard","code":"custom('result');"},"headers":[],"address":{"schema":{},"expectedResult":null,"syntax":"web-template"},"type":"Create"},"serverSideOptions":{"id":"9b566e72-93cc-3d18-a8f1-a52a44b8530c","columns":[],"rows":[],"originalRows":[],"dataEntryRunTypes":[],"datasourceType":"Standard","autoRefreshEnabled":false,"autoRefreshSystem":false,"autoRefreshTime":60,"remoteSort":"","page":1,"isBusy":false,"isFiltered":false,"isServerSide":false,"hasError":false,"splitItems":[],"rowCount":100,"pageSize":10,"tags":[],"parameters":[]},"pageExp":{"schema":{},"expectedResult":null,"syntax":"standard"},"pageSizeExp":{"schema":{},"expectedResult":null,"syntax":"standard"},"recordCountExp":{"schema":{},"expectedResult":null,"syntax":"standard"},"sortingExp":{"schema":{},"expectedResult":null,"syntax":"standard"},"downloadExp":{"schema":{},"expectedResult":null,"syntax":"web-template"},"baseUrlId":"Aquarius Services"},"parameters":[{"id":"24c0d9f9-5a33-6e1f-8784-8e432dbec314","name":"idCategory","description":"","systemType":"","defaultValue":null,"lookupItems":[],"isHidden":false,"isMultiSelect":false,"isReadOnly":false,"isOptional":false,"popupWidth":300,"isSearchAllowed":false,"ravenParameterType":"normal","ravenDatatype":"number","lookup":{"mode":"standard","showSearchBox":true,"allowSort":true,"bindings":[],"columns":[]},"rules":[],"tags":[]}]}}