{"createdAt":"2021-05-18T11:51:14.160","modifiedAt":"2021-05-18T15:17:16.028","createdBy":"TAS","modifiedBy":"TAS","title":"SE - CAT_2 - Select BIC Participant","provider":"ServicesEditorBackendServiceProvider","tags":["Raven service"],"systemTags":["RESERVED_DOCUMENT","services-editor","published-as-datasource"],"name":"SE - CAT_2 - Select BIC Participant","type":"services-editor","saved":false,"id":"634600d1-48e3-4c78-8d4c-497a48d7e477","previewId":null,"content":{"definition":{"id":"634600d1-48e3-4c78-8d4c-497a48d7e477","title":"SE - CAT_2 - Select BIC Participant","useBaseUrl":true,"publishAsDatasource":true,"serverSideDatasource":false,"dataEntryEnabled":false,"downloadEnabled":false,"expectedResultType":"Table","validated":false,"mandatoryParameters":[],"skipOnEmptyQueryString":false,"includeRawData":false,"schema":[{"name":"codCntpLogicaK","type":"string","value":"BELADEBEXXX"},{"name":"kind","type":"string","value":"participantresource#list"},{"name":"institutionName","type":"string","value":null},{"name":"multiPartecipant","type":"string","value":"Y"},{"name":"id","type":"number","value":938},{"name":"codInternal","type":"string","value":"AN1710000130646"},{"name":"codBic","type":"string","value":null},{"name":"codUser","type":"string","value":"XLS"}],"selectCall":{"method":"Get","enabled":true,"serverSide":false,"responseType":"json","transformerOut":{"schema":{},"expectedResult":null,"syntax":"standard","code":"{}"},"transformerIn":{"schema":{"datasource":{},"parameter":{},"systemParameter":{},"custom":{"result":{"fields":[null]}}},"expectedResult":null,"syntax":"standard","code":"custom('result').items;"},"headers":[],"address":{"schema":{"datasource":{},"parameter":{"serviceType":{"id":"811cb682-d19c-2493-b1d9-cc7ec16fed26"}},"systemParameter":{},"custom":{}},"expectedResult":null,"syntax":"web-template","code":"foundation/rs/partecipants/byservicecodemultipart?serviceType=<%= parameter('serviceType') %>"},"type":"Select"},"insertCall":{"method":"Put","enabled":false,"serverSide":false,"responseType":"json","transformerOut":{"schema":{},"expectedResult":null,"syntax":"standard","code":"{}"},"transformerIn":{"schema":{},"expectedResult":null,"syntax":"standard","code":"custom('result');"},"headers":[],"address":{"schema":{},"expectedResult":null,"syntax":"web-template"},"type":"Insert"},"updateCall":{"method":"Post","enabled":false,"serverSide":false,"responseType":"json","transformerOut":{"schema":{},"expectedResult":null,"syntax":"standard","code":"{}"},"transformerIn":{"schema":{},"expectedResult":null,"syntax":"standard","code":"custom('result');"},"headers":[],"address":{"schema":{},"expectedResult":null,"syntax":"web-template"},"type":"Update"},"deleteCall":{"method":"Delete","enabled":false,"serverSide":false,"responseType":"json","transformerOut":{"schema":{},"expectedResult":null,"syntax":"standard","code":"{}"},"transformerIn":{"schema":{},"expectedResult":null,"syntax":"standard","code":"custom('result');"},"headers":[],"address":{"schema":{},"expectedResult":null,"syntax":"web-template"},"type":"Delete"},"createCall":{"method":"Get","enabled":false,"serverSide":false,"responseType":"json","transformerOut":{"schema":{},"expectedResult":null,"syntax":"standard","code":"{}"},"transformerIn":{"schema":{},"expectedResult":null,"syntax":"standard","code":"custom('result');"},"headers":[],"address":{"schema":{},"expectedResult":null,"syntax":"web-template"},"type":"Create"},"serverSideOptions":{"id":"39079974-0084-4586-397c-a138ece382fd","columns":[],"rows":[],"originalRows":[],"dataEntryRunTypes":[],"datasourceType":"Standard","autoRefreshEnabled":false,"autoRefreshSystem":false,"autoRefreshTime":60,"remoteSort":"","page":1,"isBusy":false,"isFiltered":false,"isServerSide":false,"hasError":false,"splitItems":[],"rowCount":100,"pageSize":10,"tags":[],"parameters":[]},"pageExp":{"schema":{},"expectedResult":null,"syntax":"standard"},"pageSizeExp":{"schema":{},"expectedResult":null,"syntax":"standard"},"recordCountExp":{"schema":{},"expectedResult":null,"syntax":"standard"},"sortingExp":{"schema":{},"expectedResult":null,"syntax":"standard"},"downloadExp":{"schema":{},"expectedResult":null,"syntax":"web-template"},"baseUrlId":"Aquarius Services"},"parameters":[{"id":"811cb682-d19c-2493-b1d9-cc7ec16fed26","name":"serviceType","description":"","systemType":"","defaultValue":null,"lookupItems":[],"isHidden":false,"isMultiSelect":false,"isReadOnly":false,"isOptional":false,"popupWidth":300,"isSearchAllowed":false,"ravenParameterType":"normal","ravenDatatype":"string","lookup":{"mode":"standard","showSearchBox":true,"allowSort":true,"bindings":[],"columns":[]},"rules":[],"tags":[],"value":"CORR"}]}}